imagepile/__init__.py
imagepile/__main__.py
imagepile-0.0.1.dist-info/LICENSE
imagepile-0.0.1.dist-info/METADATA
imagepile-0.0.1.dist-info/WHEEL
imagepile-0.0.1.dist-info/entry_points.txt
imagepile-0.0.1.dist-info/top_level.txt
imagepile-0.0.1.dist-info/RECORD
